{
    "bounds": "[28,93][127,192]", 
    "checkable": false, 
    "checked": false, 
    "class": "android.widget.ImageView", 
    "clickable": false, 
    "enabled": true, 
    "focusable": false, 
    "focused": false, 
    "hash": "v28EMb/8GA6Pk7VeUxfJ9w==\n", 
    "height": 99, 
    "hier_level": 17, 
    "human_hash": "android.widget.ImageView_X28_Y93_W99_H99", 
    "human_readable": "android.widget.ImageView_28_93_99_99_android.widget.ImageView_fffffffffffffe7ffc3ffc3ffc3ffc7ff81ff00ff00ff00fffffffffffffffff_9d4568c009d203ab10e33ea9953a0264", 
    "image_path": "MTU5YWU5ZmQ0MjUzZDA0ZDgwMWEyNGYxOTE1MDgxMzg.png", 
    "index": "0", 
    "is_transformed": true, 
    "long-clickable": false, 
    "password": false, 
    "resource-id": "com.reddit.frontpage:id/inner_user_icon", 
    "screen_hash": "f2efe289ef808261b9980fb071e20f3f", 
    "scrollable": false, 
    "selected": false, 
    "tag_name": "android.widget.ImageView", 
    "text": "", 
    "width": 99, 
    "x": 28, 
    "y": 93
}