{
    "bounds": "[904,1729][1036,1795]", 
    "checkable": true, 
    "checked": true, 
    "class": "android.widget.Switch", 
    "clickable": false, 
    "enabled": true, 
    "focusable": false, 
    "focused": false, 
    "hash": "478u45E1EQwOhOPqD0D2Og==\n", 
    "height": 66, 
    "hier_level": 15, 
    "human_hash": "android.widget.Switch_X904_Y1729_W132_H66", 
    "human_readable": "android.widget.Switch_904_1729_132_66_android.widget.Switch_e007c01b803d807f007e007e007f00ff00ff007f007e007e807f803dc01be007_2bacc8dd7b6b40158001846c4564e0f9", 
    "image_path": "ODNmNWZmMTQwYjcxNzE5M2I2ODMwZDhhYjU0ZDUzMGU.png", 
    "index": "0", 
    "is_transformed": true, 
    "long-clickable": false, 
    "password": false, 
    "resource-id": "com.reddit.frontpage:id/switchWidget", 
    "screen_hash": "b4ac72da276b24bc610a84c82012bbed", 
    "scrollable": false, 
    "selected": false, 
    "tag_name": "android.widget.Switch", 
    "text": "ON", 
    "width": 132, 
    "x": 904, 
    "y": 1729
}