{
    "bounds": "[372,367][490,426]", 
    "checkable": false, 
    "checked": false, 
    "class": "android.widget.TextView", 
    "clickable": false, 
    "enabled": true, 
    "focusable": false, 
    "focused": false, 
    "hash": "zFCKo+0ICIiaf1R2Or9K/w==\n", 
    "height": 59, 
    "hier_level": 19, 
    "human_hash": "android.widget.TextView_X372_Y367_W118_H59", 
    "human_readable": "android.widget.TextView_372_367_118_59_android.widget.TextView_ffffffffffffffff6fff2fff690d000004426400240320006944ffffffffffff_4f113e6636baf9e2e6ab5f9a2d3031d2", 
    "image_path": "YzhiZWY5OTg4YmZjZTMzYjhiNDYzZGIwMGMwODMxM2Q.png", 
    "index": "0", 
    "is_transformed": true, 
    "long-clickable": false, 
    "password": false, 
    "screen_hash": "7f0760f744e3dcf48de7044b484ec0b7", 
    "scrollable": false, 
    "selected": true, 
    "tag_name": "android.widget.TextView", 
    "text": "Home", 
    "width": 118, 
    "x": 372, 
    "y": 367
}