{
    "bounds": "[0,896][1080,1338]", 
    "checkable": false, 
    "checked": false, 
    "class": "android.widget.LinearLayout", 
    "clickable": true, 
    "enabled": true, 
    "focusable": true, 
    "focused": false, 
    "hash": "8cPv+45Ut6n7B0qoAXqyfA==\n", 
    "height": 442, 
    "hier_level": 19, 
    "human_hash": "android.widget.LinearLayout_X0_Y896_W1080_H442", 
    "index": "2", 
    "is_transformed": true, 
    "long-clickable": false, 
    "password": false, 
    "scrollable": false, 
    "selected": false, 
    "tag_name": "android.widget.LinearLayout", 
    "text": "r/AskReddit Posted by u/ChipForClicks   7h 56Awards What is something you say to scammers instead of hanging up? 11.8k 4.4k Share", 
    "width": 1080, 
    "x": 0, 
    "y": 896
}