{
    "bounds": "[0,1697][1080,2148]", 
    "checkable": false, 
    "checked": false, 
    "class": "android.widget.ImageView", 
    "clickable": false, 
    "enabled": true, 
    "focusable": false, 
    "focused": false, 
    "hash": "NKgn3KnXcG5NZ4dplU90YQ==\n", 
    "height": 451, 
    "hier_level": 11, 
    "human_hash": "android.widget.ImageView_X0_Y1697_W1080_H451", 
    "index": "0", 
    "is_transformed": true, 
    "long-clickable": false, 
    "password": false, 
    "resource-id": "com.reddit.frontpage:id/background", 
    "scrollable": false, 
    "selected": false, 
    "tag_name": "android.widget.ImageView", 
    "text": "", 
    "width": 1080, 
    "x": 0, 
    "y": 1697
}